{
  "843416715": {
    "telegramId": 843416715,
    "username": "@dittajayaww",
    "fotoFileId": "AgACAgUAAxkBAAIBuGo3SYyMHc78f2exSyyYitwwJa3KAAK4DmsbqbS4VTAltoRca8isAQADAgADeQADPAQ",
    "targetRole": "fullupdate",
    "registeredBy": null,
    "registeredByName": "Mandiri",
    "registeredByRole": null,
    "approved": false,
    "timestamp": "2026-06-21T02:35:44.114Z"
  },
  "8191534265": {
    "telegramId": 8191534265,
    "username": "@prradistyy",
    "fotoFileId": "AgACAgUAAxkBAAICA2o3TXg1jDqrawonkn4ZiKy2r_X3AAJtEmsb8KS5VT0qhIq8bz2PAQADAgADeQADPAQ",
    "targetRole": "reseller",
    "registeredBy": null,
    "registeredByName": "Mandiri",
    "registeredByRole": null,
    "approved": true,
    "timestamp": "2026-06-21T02:33:28.428Z",
    "approvedBy": 1348415353,
    "approvedAt": "2026-06-21T02:34:00.563Z"
  },
  "8121694751": {
    "telegramId": 8121694751,
    "username": "@Fataofiicial",
    "fotoFileId": "AgACAgUAAxkBAAICBmo3Tbl7_Xqi7sg23fUmmtN_W-gwAAIgD2sbJxK5VU6gi2sJO_6dAQADAgADeQADPAQ",
    "targetRole": "reseller",
    "registeredBy": null,
    "registeredByName": "Mandiri",
    "registeredByRole": null,
    "approved": false,
    "timestamp": "2026-06-21T02:34:33.581Z"
  }
}